Metadata-Version: 1.0
Name: packagetenssor
Version: 0.5
Summary: notihng as such
Home-page: UNKNOWN
Author: edosnahb
Author-email: UNKNOWN
License: UNKNOWN
Platform: UNKNOWN
